novavision/__init__.py
novavision/cli.py
novavision/docker_manager.py
novavision/installer.py
novavision/logger.py
novavision/utils.py
novavision_cli-0.0.10.dist-info/licenses/LICENSE
novavision_cli-0.0.10.dist-info/METADATA
novavision_cli-0.0.10.dist-info/WHEEL
novavision_cli-0.0.10.dist-info/entry_points.txt
novavision_cli-0.0.10.dist-info/top_level.txt
novavision_cli-0.0.10.dist-info/RECORD
