Metadata-Version: 2.4
Name: novavision-cli
Version: 0.0.10
Summary: NovaVision CLI for handling servers.
Author: İlhan Kaan Yazıcıoğlu
Author-email: ilhan.kaan.yazicioglu@diginova.com.tr
License: Apache-2.0
Classifier: Programming Language :: Python :: 3
Classifier: License :: OSI Approved :: Apache Software License
Classifier: Operating System :: OS Independent
Requires-Python: >=3.8
License-File: LICENSE
Requires-Dist: requests==2.32.3
Requires-Dist: psutil==6.1.1
Requires-Dist: docker<7,>=6.1.3
Requires-Dist: rich==13.9.4
Requires-Dist: pyyaml==6.0.2
Requires-Dist: pyobjc; sys_platform == "darwin"
Dynamic: author
Dynamic: author-email
Dynamic: classifier
Dynamic: description
Dynamic: description-content-type
Dynamic: license
Dynamic: license-file
Dynamic: provides-extra
Dynamic: requires-dist
Dynamic: requires-python
Dynamic: summary
